{
  "id": "f2_pro_e_ii",
  "name": "Ninebot F2 Pro E II",
  "brand": "Segway",
  "battery_capacity_wh": 460,
  "motor_power_nominal_w": 450,
  "motor_power_max_w": 900,
  "max_speed_kmh": 25,
  "max_range_km": 65,
  "max_payload_kg": 120,
  "unit_weight_kg": 17.75,
  "foldable": true,
  "front_brake": "mechanical_disc",
  "rear_brake": "electronic",
  "tire_size_inch": 10,
  "tire_type": "tubeless",
  "suspension": "front",
  "ip_body": "IPX5",
  "ip_battery": "IPX6",
  "dimensions_open_mm": "1143 x 570 x 1237",
  "dimensions_folded_mm": "1144 x 570 x 507",
  "image_url": "/images/f2_pro_e_ii.png"
}

